[{"lawd_cd":"11650","deal_ym":"202005","apt_name":"래미안서초에스티지","deal_date":"2020-05-01","price_man":209000,"area_m2":83.6,"floor":9,"build_year":2016,"dong_name":"서초동","jibun":"1332-13"},{"lawd_cd":"11650","deal_ym":"202005","apt_name":"반포래미안아이파크","deal_date":"2020-05-01","price_man":260000,"area_m2":99.92,"floor":29,"build_year":2018,"dong_name":"반포동","jibun":"1341"},{"lawd_cd":"11650","deal_ym":"202005","apt_name":"반포자이","deal_date":"2020-05-01","price_man":195000,"area_m2":59.98,"floor":7,"build_year":2009,"dong_name":"반포동","jibun":"20-43"},{"lawd_cd":"11650","deal_ym":"202005","apt_name":"서초교대e편한세상","deal_date":"2020-05-01","price_man":150000,"area_m2":59.9,"floor":10,"build_year":2010,"dong_name":"서초동","jibun":"1686-9"},{"lawd_cd":"11650","deal_ym":"202005","apt_name":"에이아이디차관주택","deal_date":"2020-05-01","price_man":216000,"area_m2":72.51,"floor":4,"build_year":1974,"dong_name":"반포동","jibun":"968"},{"lawd_cd":"11650","deal_ym":"202005","apt_name":"한진로즈힐","deal_date":"2020-05-01","price_man":147500,"area_m2":84.376,"floor":4,"build_year":2005,"dong_name":"방배동","jibun":"3276"},{"lawd_cd":"11650","deal_ym":"202005","apt_name":"반포자이","deal_date":"2020-05-02","price_man":258000,"area_m2":84.998,"floor":22,"build_year":2009,"dong_name":"반포동","jibun":"20-43"},{"lawd_cd":"11650","deal_ym":"202005","apt_name":"서초훼미리하우스","deal_date":"2020-05-02","price_man":89700,"area_m2":59.49,"floor":9,"build_year":2017,"dong_name":"방배동","jibun":"917-4"},{"lawd_cd":"11650","deal_ym":"202005","apt_name":"신반포2","deal_date":"2020-05-02","price_man":312000,"area_m2":150.58,"floor":6,"build_year":1978,"dong_name":"잠원동","jibun":"73"},{"lawd_cd":"11650","deal_ym":"202005","apt_name":"한라비발디스튜디오193","deal_date":"2020-05-02","price_man":20000,"area_m2":19.99,"floor":6,"build_year":2013,"dong_name":"서초동","jibun":"1363-25"},{"lawd_cd":"11650","deal_ym":"202005","apt_name":"래미안퍼스티지","deal_date":"2020-05-03","price_man":279000,"area_m2":84.93,"floor":22,"build_year":2009,"dong_name":"반포동","jibun":"18-1"},{"lawd_cd":"11650","deal_ym":"202005","apt_name":"방배동갤러리하우스3","deal_date":"2020-05-04","price_man":102000,"area_m2":103.65,"floor":3,"build_year":2003,"dong_name":"방배동","jibun":"1-7"},{"lawd_cd":"11650","deal_ym":"202005","apt_name":"신반포4","deal_date":"2020-05-04","price_man":217000,"area_m2":107.39,"floor":9,"build_year":1979,"dong_name":"잠원동","jibun":"70"},{"lawd_cd":"11650","deal_ym":"202005","apt_name":"우성아파트","deal_date":"2020-05-04","price_man":135000,"area_m2":59.93,"floor":20,"build_year":1998,"dong_name":"서초동","jibun":"1326-17"},{"lawd_cd":"11650","deal_ym":"202005","apt_name":"대림서초리시온","deal_date":"2020-05-05","price_man":47000,"area_m2":48.2,"floor":12,"build_year":2003,"dong_name":"서초동","jibun":"1671-5"},{"lawd_cd":"11650","deal_ym":"202005","apt_name":"래미안퍼스티지","deal_date":"2020-05-05","price_man":192500,"area_m2":59.96,"floor":12,"build_year":2009,"dong_name":"반포동","jibun":"18-1"},{"lawd_cd":"11650","deal_ym":"202005","apt_name":"반포리체","deal_date":"2020-05-05","price_man":256000,"area_m2":106.148,"floor":25,"build_year":2010,"dong_name":"반포동","jibun":"30-26"},{"lawd_cd":"11650","deal_ym":"202005","apt_name":"반포센트럴자이","deal_date":"2020-05-05","price_man":212000,"area_m2":59.97,"floor":18,"build_year":2020,"dong_name":"잠원동","jibun":"162"},{"lawd_cd":"11650","deal_ym":"202005","apt_name":"반포자이","deal_date":"2020-05-05","price_man":260000,"area_m2":84.943,"floor":11,"build_year":2009,"dong_name":"반포동","jibun":"20-43"},{"lawd_cd":"11650","deal_ym":"202005","apt_name":"신반포2","deal_date":"2020-05-05","price_man":186000,"area_m2":79.42,"floor":12,"build_year":1978,"dong_name":"잠원동","jibun":"73"},{"lawd_cd":"11650","deal_ym":"202005","apt_name":"신반포청구","deal_date":"2020-05-05","price_man":140000,"area_m2":59.91,"floor":2,"build_year":1998,"dong_name":"잠원동","jibun":"63-2"},{"lawd_cd":"11650","deal_ym":"202005","apt_name":"중앙하이츠","deal_date":"2020-05-05","price_man":149800,"area_m2":75.44,"floor":15,"build_year":1998,"dong_name":"잠원동","jibun":"71-17"},{"lawd_cd":"11650","deal_ym":"202005","apt_name":"한신로얄","deal_date":"2020-05-05","price_man":148500,"area_m2":81.23,"floor":2,"build_year":1992,"dong_name":"잠원동","jibun":"63-34"},{"lawd_cd":"11650","deal_ym":"202005","apt_name":"현대멤피스","deal_date":"2020-05-05","price_man":172000,"area_m2":133.31,"floor":1,"build_year":2001,"dong_name":"방배동","jibun":"772-13"},{"lawd_cd":"11650","deal_ym":"202005","apt_name":"강변","deal_date":"2020-05-06","price_man":154000,"area_m2":84.53,"floor":2,"build_year":1987,"dong_name":"잠원동","jibun":"53-15"},{"lawd_cd":"11650","deal_ym":"202005","apt_name":"래미안서초에스티지S","deal_date":"2020-05-06","price_man":220000,"area_m2":84.8,"floor":17,"build_year":2018,"dong_name":"서초동","jibun":"1754"},{"lawd_cd":"11650","deal_ym":"202005","apt_name":"반포주공1단지","deal_date":"2020-05-06","price_man":335000,"area_m2":106.26,"floor":3,"build_year":1973,"dong_name":"반포동","jibun":"757"},{"lawd_cd":"11650","deal_ym":"202005","apt_name":"서초트라팰리스","deal_date":"2020-05-06","price_man":134000,"area_m2":133.05,"floor":6,"build_year":2005,"dong_name":"서초동","jibun":"1344-13"},{"lawd_cd":"11650","deal_ym":"202005","apt_name":"아크로리버파크","deal_date":"2020-05-06","price_man":283000,"area_m2":84.99,"floor":7,"build_year":2016,"dong_name":"반포동","jibun":"2-12"},{"lawd_cd":"11650","deal_ym":"202005","apt_name":"우성아파트","deal_date":"2020-05-06","price_man":152800,"area_m2":84.93,"floor":19,"build_year":1998,"dong_name":"서초동","jibun":"1326-17"},{"lawd_cd":"11650","deal_ym":"202005","apt_name":"현대빌라트","deal_date":"2020-05-06","price_man":180000,"area_m2":164.83,"floor":7,"build_year":1994,"dong_name":"서초동","jibun":"1495-1"},{"lawd_cd":"11650","deal_ym":"202005","apt_name":"래미안퍼스티지","deal_date":"2020-05-07","price_man":402500,"area_m2":198.22,"floor":13,"build_year":2009,"dong_name":"반포동","jibun":"18-1"},{"lawd_cd":"11650","deal_ym":"202005","apt_name":"래미안퍼스티지","deal_date":"2020-05-07","price_man":282000,"area_m2":84.93,"floor":16,"build_year":2009,"dong_name":"반포동","jibun":"18-1"},{"lawd_cd":"11650","deal_ym":"202005","apt_name":"브라운스톤방배","deal_date":"2020-05-07","price_man":151500,"area_m2":84.96,"floor":8,"build_year":2005,"dong_name":"방배동","jibun":"899-16"},{"lawd_cd":"11650","deal_ym":"202005","apt_name":"서초동삼성쉐르빌2","deal_date":"2020-05-07","price_man":30500,"area_m2":35.22,"floor":13,"build_year":2002,"dong_name":"서초동","jibun":"1330"},{"lawd_cd":"11650","deal_ym":"202005","apt_name":"서초이에스에이3차","deal_date":"2020-05-07","price_man":80000,"area_m2":59.4,"floor":10,"build_year":2002,"dong_name":"방배동","jibun":"1006-1"},{"lawd_cd":"11650","deal_ym":"202005","apt_name":"신반포2","deal_date":"2020-05-07","price_man":240000,"area_m2":107.31,"floor":9,"build_year":1978,"dong_name":"잠원동","jibun":"73"},{"lawd_cd":"11650","deal_ym":"202005","apt_name":"신반포2","deal_date":"2020-05-07","price_man":177000,"area_m2":68.91,"floor":10,"build_year":1978,"dong_name":"잠원동","jibun":"73"},{"lawd_cd":"11650","deal_ym":"202005","apt_name":"신반포2","deal_date":"2020-05-07","price_man":260000,"area_m2":137.66,"floor":12,"build_year":1978,"dong_name":"잠원동","jibun":"73"},{"lawd_cd":"11650","deal_ym":"202005","apt_name":"현대성우주상복합아파트","deal_date":"2020-05-07","price_man":138500,"area_m2":133.48,"floor":5,"build_year":2002,"dong_name":"서초동","jibun":"1316-15"},{"lawd_cd":"11650","deal_ym":"202005","apt_name":"래미안퍼스티지","deal_date":"2020-05-08","price_man":191000,"area_m2":59.89,"floor":3,"build_year":2009,"dong_name":"반포동","jibun":"18-1"},{"lawd_cd":"11650","deal_ym":"202005","apt_name":"레베빌(86-10)","deal_date":"2020-05-08","price_man":230000,"area_m2":244.15,"floor":3,"build_year":1998,"dong_name":"반포동","jibun":"86-10"},{"lawd_cd":"11650","deal_ym":"202005","apt_name":"방배대우멤버스카운티(809-17)","deal_date":"2020-05-08","price_man":137000,"area_m2":125.52,"floor":2,"build_year":2003,"dong_name":"방배동","jibun":"809-17"},{"lawd_cd":"11650","deal_ym":"202005","apt_name":"에이아이디차관주택","deal_date":"2020-05-08","price_man":213000,"area_m2":72.51,"floor":5,"build_year":1974,"dong_name":"반포동","jibun":"968"},{"lawd_cd":"11650","deal_ym":"202005","apt_name":"현대성우주상복합아파트","deal_date":"2020-05-08","price_man":155000,"area_m2":161.91,"floor":17,"build_year":2002,"dong_name":"서초동","jibun":"1316-15"},{"lawd_cd":"11650","deal_ym":"202005","apt_name":"대우(효령)","deal_date":"2020-05-09","price_man":134000,"area_m2":84.91,"floor":4,"build_year":1992,"dong_name":"방배동","jibun":"1038"},{"lawd_cd":"11650","deal_ym":"202005","apt_name":"동아","deal_date":"2020-05-09","price_man":163000,"area_m2":59.8,"floor":4,"build_year":2002,"dong_name":"잠원동","jibun":"157"},{"lawd_cd":"11650","deal_ym":"202005","apt_name":"동아","deal_date":"2020-05-09","price_man":163000,"area_m2":59.8,"floor":15,"build_year":2002,"dong_name":"잠원동","jibun":"157"},{"lawd_cd":"11650","deal_ym":"202005","apt_name":"래미안퍼스티지","deal_date":"2020-05-09","price_man":261000,"area_m2":84.85,"floor":16,"build_year":2009,"dong_name":"반포동","jibun":"18-1"},{"lawd_cd":"11650","deal_ym":"202005","apt_name":"롯데캐슬클래식","deal_date":"2020-05-09","price_man":183000,"area_m2":84.98,"floor":17,"build_year":2006,"dong_name":"서초동","jibun":"1312-3"},{"lawd_cd":"11650","deal_ym":"202005","apt_name":"반포힐스테이트","deal_date":"2020-05-09","price_man":330000,"area_m2":155.38,"floor":16,"build_year":2012,"dong_name":"반포동","jibun":"16-6"},{"lawd_cd":"11650","deal_ym":"202005","apt_name":"삼풍아파트","deal_date":"2020-05-09","price_man":183000,"area_m2":79.47,"floor":14,"build_year":1988,"dong_name":"서초동","jibun":"1685"},{"lawd_cd":"11650","deal_ym":"202005","apt_name":"서리풀e편한세상","deal_date":"2020-05-09","price_man":190000,"area_m2":84.97,"floor":5,"build_year":2010,"dong_name":"방배동","jibun":"906-13"},{"lawd_cd":"11650","deal_ym":"202005","apt_name":"서초두산위브트레지움","deal_date":"2020-05-09","price_man":170000,"area_m2":84.62,"floor":14,"build_year":2008,"dong_name":"서초동","jibun":"1310-4"},{"lawd_cd":"11650","deal_ym":"202005","apt_name":"서초아트자이","deal_date":"2020-05-09","price_man":183000,"area_m2":144.3141,"floor":12,"build_year":2009,"dong_name":"서초동","jibun":"1583-10"},{"lawd_cd":"11650","deal_ym":"202005","apt_name":"서초태동스위트","deal_date":"2020-05-09","price_man":89000,"area_m2":100.02,"floor":3,"build_year":2001,"dong_name":"서초동","jibun":"1668-1"},{"lawd_cd":"11650","deal_ym":"202005","apt_name":"아크로리버파크","deal_date":"2020-05-09","price_man":205000,"area_m2":59.98,"floor":20,"build_year":2016,"dong_name":"반포동","jibun":"2-12"},{"lawd_cd":"11650","deal_ym":"202005","apt_name":"코오롱","deal_date":"2020-05-09","price_man":89500,"area_m2":52.47,"floor":3,"build_year":1994,"dong_name":"우면동","jibun":"70"},{"lawd_cd":"11650","deal_ym":"202005","apt_name":"훼미리","deal_date":"2020-05-09","price_man":172000,"area_m2":84.83,"floor":11,"build_year":1992,"dong_name":"잠원동","jibun":"51"},{"lawd_cd":"11650","deal_ym":"202005","apt_name":"래미안신반포리오센트","deal_date":"2020-05-10","price_man":305000,"area_m2":133.37,"floor":12,"build_year":2019,"dong_name":"잠원동","jibun":"161"},{"lawd_cd":"11650","deal_ym":"202005","apt_name":"서리풀e편한세상","deal_date":"2020-05-10","price_man":189000,"area_m2":84.97,"floor":2,"build_year":2010,"dong_name":"방배동","jibun":"906-13"},{"lawd_cd":"11650","deal_ym":"202005","apt_name":"신반포10","deal_date":"2020-05-10","price_man":174000,"area_m2":54.11,"floor":9,"build_year":1981,"dong_name":"잠원동","jibun":"58-16"},{"lawd_cd":"11650","deal_ym":"202005","apt_name":"대성유니드","deal_date":"2020-05-11","price_man":140500,"area_m2":122.111,"floor":1,"build_year":2004,"dong_name":"서초동","jibun":"1641-3"},{"lawd_cd":"11650","deal_ym":"202005","apt_name":"반포자이","deal_date":"2020-05-11","price_man":255000,"area_m2":84.982,"floor":23,"build_year":2009,"dong_name":"반포동","jibun":"20-43"},{"lawd_cd":"11650","deal_ym":"202005","apt_name":"방배래미안타워","deal_date":"2020-05-11","price_man":149800,"area_m2":103.34,"floor":22,"build_year":2005,"dong_name":"방배동","jibun":"485-3"},{"lawd_cd":"11650","deal_ym":"202005","apt_name":"삼익","deal_date":"2020-05-11","price_man":200000,"area_m2":151.54,"floor":11,"build_year":1981,"dong_name":"방배동","jibun":"1018-1"},{"lawd_cd":"11650","deal_ym":"202005","apt_name":"신반포2","deal_date":"2020-05-11","price_man":200000,"area_m2":92.2,"floor":8,"build_year":1978,"dong_name":"잠원동","jibun":"73"},{"lawd_cd":"11650","deal_ym":"202005","apt_name":"신반포4","deal_date":"2020-05-11","price_man":268000,"area_m2":137.1,"floor":3,"build_year":1979,"dong_name":"잠원동","jibun":"70"},{"lawd_cd":"11650","deal_ym":"202005","apt_name":"동아","deal_date":"2020-05-12","price_man":176000,"area_m2":84.91,"floor":11,"build_year":2002,"dong_name":"잠원동","jibun":"157"},{"lawd_cd":"11650","deal_ym":"202005","apt_name":"래미안퍼스티지","deal_date":"2020-05-12","price_man":450000,"area_m2":222.76,"floor":18,"build_year":2009,"dong_name":"반포동","jibun":"18-1"},{"lawd_cd":"11650","deal_ym":"202005","apt_name":"반포리체","deal_date":"2020-05-12","price_man":241000,"area_m2":84.967,"floor":19,"build_year":2010,"dong_name":"반포동","jibun":"30-26"},{"lawd_cd":"11650","deal_ym":"202005","apt_name":"삼성서초가든스위트","deal_date":"2020-05-12","price_man":262500,"area_m2":181.5,"floor":6,"build_year":2000,"dong_name":"서초동","jibun":"1326"},{"lawd_cd":"11650","deal_ym":"202005","apt_name":"아크로리버파크","deal_date":"2020-05-12","price_man":287000,"area_m2":84.95,"floor":6,"build_year":2016,"dong_name":"반포동","jibun":"2-12"},{"lawd_cd":"11650","deal_ym":"202005","apt_name":"탑빌라트","deal_date":"2020-05-12","price_man":142000,"area_m2":208.53,"floor":4,"build_year":1991,"dong_name":"방배동","jibun":"797-1"},{"lawd_cd":"11650","deal_ym":"202005","apt_name":"한라비발디스튜디오193","deal_date":"2020-05-12","price_man":27000,"area_m2":19.99,"floor":10,"build_year":2013,"dong_name":"서초동","jibun":"1363-25"},{"lawd_cd":"11650","deal_ym":"202005","apt_name":"반포자이","deal_date":"2020-05-13","price_man":253000,"area_m2":84.943,"floor":29,"build_year":2009,"dong_name":"반포동","jibun":"20-43"},{"lawd_cd":"11650","deal_ym":"202005","apt_name":"삼풍아파트","deal_date":"2020-05-13","price_man":173000,"area_m2":79.47,"floor":9,"build_year":1988,"dong_name":"서초동","jibun":"1685"},{"lawd_cd":"11650","deal_ym":"202005","apt_name":"삼풍아파트","deal_date":"2020-05-13","price_man":178000,"area_m2":79.47,"floor":11,"build_year":1988,"dong_name":"서초동","jibun":"1685"},{"lawd_cd":"11650","deal_ym":"202005","apt_name":"서초드림하이츠","deal_date":"2020-05-13","price_man":72000,"area_m2":77.25,"floor":5,"build_year":2003,"dong_name":"서초동","jibun":"1617-26"},{"lawd_cd":"11650","deal_ym":"202005","apt_name":"서초이에스에이3차","deal_date":"2020-05-13","price_man":81000,"area_m2":59.4,"floor":11,"build_year":2002,"dong_name":"방배동","jibun":"1006-1"},{"lawd_cd":"11650","deal_ym":"202005","apt_name":"서초트라팰리스","deal_date":"2020-05-13","price_man":134300,"area_m2":107.69,"floor":7,"build_year":2005,"dong_name":"서초동","jibun":"1344-13"},{"lawd_cd":"11650","deal_ym":"202005","apt_name":"아크로리버파크","deal_date":"2020-05-13","price_man":316500,"area_m2":84.97,"floor":18,"build_year":2016,"dong_name":"반포동","jibun":"2-12"},{"lawd_cd":"11650","deal_ym":"202005","apt_name":"대호프레조빌","deal_date":"2020-05-14","price_man":135000,"area_m2":236.84,"floor":5,"build_year":1999,"dong_name":"서초동","jibun":"1604-19"},{"lawd_cd":"11650","deal_ym":"202005","apt_name":"래미안퍼스티지","deal_date":"2020-05-14","price_man":215000,"area_m2":59.96,"floor":11,"build_year":2009,"dong_name":"반포동","jibun":"18-1"},{"lawd_cd":"11650","deal_ym":"202005","apt_name":"삼풍아파트","deal_date":"2020-05-14","price_man":250000,"area_m2":165.92,"floor":1,"build_year":1988,"dong_name":"서초동","jibun":"1685"},{"lawd_cd":"11650","deal_ym":"202005","apt_name":"삼호2","deal_date":"2020-05-14","price_man":164000,"area_m2":127.94,"floor":12,"build_year":1976,"dong_name":"방배동","jibun":"758-4"},{"lawd_cd":"11650","deal_ym":"202005","apt_name":"서초래미안","deal_date":"2020-05-14","price_man":167000,"area_m2":84.95,"floor":8,"build_year":2003,"dong_name":"서초동","jibun":"1682"},{"lawd_cd":"11650","deal_ym":"202005","apt_name":"서초힐스","deal_date":"2020-05-14","price_man":105000,"area_m2":59.97,"floor":5,"build_year":2012,"dong_name":"우면동","jibun":"773"},{"lawd_cd":"11650","deal_ym":"202005","apt_name":"신화","deal_date":"2020-05-14","price_man":137000,"area_m2":84.85,"floor":5,"build_year":1997,"dong_name":"잠원동","jibun":"54-7"},{"lawd_cd":"11650","deal_ym":"202005","apt_name":"프레스턴-2(1506-42)","deal_date":"2020-05-14","price_man":142706,"area_m2":141.37,"floor":2,"build_year":2006,"dong_name":"서초동","jibun":"1506-42"},{"lawd_cd":"11650","deal_ym":"202005","apt_name":"한라비발디스튜디오193","deal_date":"2020-05-14","price_man":25000,"area_m2":19.99,"floor":9,"build_year":2013,"dong_name":"서초동","jibun":"1363-25"},{"lawd_cd":"11650","deal_ym":"202005","apt_name":"래미안방배아트힐(1008-2)","deal_date":"2020-05-15","price_man":170000,"area_m2":127.31,"floor":16,"build_year":2004,"dong_name":"방배동","jibun":"1008-2"},{"lawd_cd":"11650","deal_ym":"202005","apt_name":"래미안퍼스티지","deal_date":"2020-05-15","price_man":266000,"area_m2":84.85,"floor":3,"build_year":2009,"dong_name":"반포동","jibun":"18-1"},{"lawd_cd":"11650","deal_ym":"202005","apt_name":"래미안퍼스티지","deal_date":"2020-05-15","price_man":282500,"area_m2":84.93,"floor":9,"build_year":2009,"dong_name":"반포동","jibun":"18-1"},{"lawd_cd":"11650","deal_ym":"202005","apt_name":"반포자이","deal_date":"2020-05-15","price_man":350000,"area_m2":194.515,"floor":17,"build_year":2009,"dong_name":"반포동","jibun":"20-43"},{"lawd_cd":"11650","deal_ym":"202005","apt_name":"방배1차현대홈타운","deal_date":"2020-05-15","price_man":123000,"area_m2":59.94,"floor":12,"build_year":1999,"dong_name":"방배동","jibun":"1344"},{"lawd_cd":"11650","deal_ym":"202005","apt_name":"서초대우아이빌","deal_date":"2020-05-15","price_man":30500,"area_m2":35.307,"floor":4,"build_year":2003,"dong_name":"서초동","jibun":"1675-11"},{"lawd_cd":"11650","deal_ym":"202005","apt_name":"서초더샵포레","deal_date":"2020-05-15","price_man":139000,"area_m2":101.34,"floor":11,"build_year":2014,"dong_name":"내곡동","jibun":"411"},{"lawd_cd":"11650","deal_ym":"202005","apt_name":"서초롯데캐슬프레지던트","deal_date":"2020-05-15","price_man":210000,"area_m2":119.13,"floor":16,"build_year":2014,"dong_name":"서초동","jibun":"1681-8"},{"lawd_cd":"11650","deal_ym":"202005","apt_name":"서초포레스타5단지","deal_date":"2020-05-15","price_man":148000,"area_m2":101.35,"floor":6,"build_year":2014,"dong_name":"신원동","jibun":"579"},{"lawd_cd":"11650","deal_ym":"202005","apt_name":"아크로리버파크","deal_date":"2020-05-15","price_man":465000,"area_m2":164.39,"floor":11,"build_year":2016,"dong_name":"반포동","jibun":"2-12"},{"lawd_cd":"11650","deal_ym":"202005","apt_name":"아크로비스타","deal_date":"2020-05-15","price_man":232000,"area_m2":205.07,"floor":23,"build_year":2004,"dong_name":"서초동","jibun":"1685-3"},{"lawd_cd":"11650","deal_ym":"202005","apt_name":"카사벨라(939-9)","deal_date":"2020-05-15","price_man":80000,"area_m2":148.37,"floor":6,"build_year":2005,"dong_name":"방배동","jibun":"939-9"},{"lawd_cd":"11650","deal_ym":"202005","apt_name":"트라움하우스2","deal_date":"2020-05-15","price_man":250000,"area_m2":267.08,"floor":3,"build_year":1996,"dong_name":"서초동","jibun":"1495-2"},{"lawd_cd":"11650","deal_ym":"202005","apt_name":"대우아이빌","deal_date":"2020-05-16","price_man":47500,"area_m2":27.07,"floor":4,"build_year":2001,"dong_name":"잠원동","jibun":"42-13"},{"lawd_cd":"11650","deal_ym":"202005","apt_name":"래미안퍼스티지","deal_date":"2020-05-16","price_man":489000,"area_m2":222.76,"floor":8,"build_year":2009,"dong_name":"반포동","jibun":"18-1"},{"lawd_cd":"11650","deal_ym":"202005","apt_name":"반포미도","deal_date":"2020-05-16","price_man":175000,"area_m2":84.96,"floor":13,"build_year":1987,"dong_name":"반포동","jibun":"60-4"},{"lawd_cd":"11650","deal_ym":"202005","apt_name":"반포자이","deal_date":"2020-05-16","price_man":355000,"area_m2":194.515,"floor":4,"build_year":2009,"dong_name":"반포동","jibun":"20-43"},{"lawd_cd":"11650","deal_ym":"202005","apt_name":"반포푸르지오","deal_date":"2020-05-16","price_man":180000,"area_m2":84.82,"floor":7,"build_year":2000,"dong_name":"반포동","jibun":"10"},{"lawd_cd":"11650","deal_ym":"202005","apt_name":"래미안퍼스티지","deal_date":"2020-05-17","price_man":285000,"area_m2":84.93,"floor":25,"build_year":2009,"dong_name":"반포동","jibun":"18-1"},{"lawd_cd":"11650","deal_ym":"202005","apt_name":"동아","deal_date":"2020-05-18","price_man":149900,"area_m2":59.92,"floor":4,"build_year":2002,"dong_name":"잠원동","jibun":"157"},{"lawd_cd":"11650","deal_ym":"202005","apt_name":"반포동피카소빌","deal_date":"2020-05-18","price_man":150000,"area_m2":166.84,"floor":2,"build_year":2004,"dong_name":"반포동","jibun":"79-5"},{"lawd_cd":"11650","deal_ym":"202005","apt_name":"반포훼미리(101동)","deal_date":"2020-05-18","price_man":126000,"area_m2":108.5,"floor":9,"build_year":2002,"dong_name":"반포동","jibun":"713-1"},{"lawd_cd":"11650","deal_ym":"202005","apt_name":"서초현대","deal_date":"2020-05-18","price_man":118800,"area_m2":59.4,"floor":9,"build_year":1999,"dong_name":"서초동","jibun":"1648-2"},{"lawd_cd":"11650","deal_ym":"202005","apt_name":"포레스빌","deal_date":"2020-05-18","price_man":83000,"area_m2":84.38,"floor":5,"build_year":2002,"dong_name":"양재동","jibun":"119-3"},{"lawd_cd":"11650","deal_ym":"202005","apt_name":"풍림아이원플러스","deal_date":"2020-05-18","price_man":27000,"area_m2":34.4237,"floor":15,"build_year":2004,"dong_name":"서초동","jibun":"1338-1"},{"lawd_cd":"11650","deal_ym":"202005","apt_name":"서초3차e편한세상","deal_date":"2020-05-19","price_man":162000,"area_m2":158.24,"floor":8,"build_year":2005,"dong_name":"서초동","jibun":"1467-37"},{"lawd_cd":"11650","deal_ym":"202005","apt_name":"서초한신리빙타워","deal_date":"2020-05-19","price_man":48000,"area_m2":47.87,"floor":8,"build_year":1999,"dong_name":"서초동","jibun":"1533"},{"lawd_cd":"11650","deal_ym":"202005","apt_name":"래미안퍼스티지","deal_date":"2020-05-20","price_man":260000,"area_m2":84.85,"floor":20,"build_year":2009,"dong_name":"반포동","jibun":"18-1"},{"lawd_cd":"11650","deal_ym":"202005","apt_name":"래미안퍼스티지","deal_date":"2020-05-20","price_man":279500,"area_m2":84.93,"floor":29,"build_year":2009,"dong_name":"반포동","jibun":"18-1"},{"lawd_cd":"11650","deal_ym":"202005","apt_name":"롯데캐슬클래식","deal_date":"2020-05-20","price_man":164000,"area_m2":74.3,"floor":5,"build_year":2006,"dong_name":"서초동","jibun":"1312-3"},{"lawd_cd":"11650","deal_ym":"202005","apt_name":"반포미도","deal_date":"2020-05-20","price_man":177000,"area_m2":84.96,"floor":8,"build_year":1987,"dong_name":"반포동","jibun":"60-4"},{"lawd_cd":"11650","deal_ym":"202005","apt_name":"삼풍아파트","deal_date":"2020-05-20","price_man":175500,"area_m2":79.47,"floor":14,"build_year":1988,"dong_name":"서초동","jibun":"1685"},{"lawd_cd":"11650","deal_ym":"202005","apt_name":"서초동대우디오빌프라임","deal_date":"2020-05-20","price_man":92000,"area_m2":81.97,"floor":14,"build_year":2005,"dong_name":"서초동","jibun":"1337-22"},{"lawd_cd":"11650","deal_ym":"202005","apt_name":"서초래미안","deal_date":"2020-05-20","price_man":191500,"area_m2":111.32,"floor":9,"build_year":2003,"dong_name":"서초동","jibun":"1682"},{"lawd_cd":"11650","deal_ym":"202005","apt_name":"서초푸르지오써밋","deal_date":"2020-05-20","price_man":179000,"area_m2":59.62,"floor":34,"build_year":2017,"dong_name":"서초동","jibun":"1311-10"},{"lawd_cd":"11650","deal_ym":"202005","apt_name":"신동아아파트(1차)","deal_date":"2020-05-20","price_man":190000,"area_m2":102.21,"floor":8,"build_year":1978,"dong_name":"서초동","jibun":"1333"},{"lawd_cd":"11650","deal_ym":"202005","apt_name":"아크로리버파크","deal_date":"2020-05-20","price_man":370000,"area_m2":112.93,"floor":15,"build_year":2016,"dong_name":"반포동","jibun":"2-12"},{"lawd_cd":"11650","deal_ym":"202005","apt_name":"아크로비스타","deal_date":"2020-05-20","price_man":307500,"area_m2":242.26,"floor":31,"build_year":2004,"dong_name":"서초동","jibun":"1685-3"},{"lawd_cd":"11650","deal_ym":"202005","apt_name":"노블하임","deal_date":"2020-05-21","price_man":240150,"area_m2":242.77,"floor":2,"build_year":2003,"dong_name":"방배동","jibun":"807-5"},{"lawd_cd":"11650","deal_ym":"202005","apt_name":"대림서초리시온","deal_date":"2020-05-21","price_man":36500,"area_m2":39.9,"floor":11,"build_year":2003,"dong_name":"서초동","jibun":"1671-5"},{"lawd_cd":"11650","deal_ym":"202005","apt_name":"롯데캐슬헤론","deal_date":"2020-05-21","price_man":149500,"area_m2":148.9,"floor":3,"build_year":2006,"dong_name":"방배동","jibun":"754-1"},{"lawd_cd":"11650","deal_ym":"202005","apt_name":"반포자이","deal_date":"2020-05-21","price_man":258000,"area_m2":84.982,"floor":3,"build_year":2009,"dong_name":"반포동","jibun":"20-43"},{"lawd_cd":"11650","deal_ym":"202005","apt_name":"방배현대멤피스2","deal_date":"2020-05-21","price_man":117400,"area_m2":162.8,"floor":5,"build_year":2002,"dong_name":"방배동","jibun":"982-1"},{"lawd_cd":"11650","deal_ym":"202005","apt_name":"신반포청구","deal_date":"2020-05-21","price_man":172000,"area_m2":84.86,"floor":7,"build_year":1998,"dong_name":"잠원동","jibun":"63-2"},{"lawd_cd":"11650","deal_ym":"202005","apt_name":"양재","deal_date":"2020-05-21","price_man":58000,"area_m2":83.17,"floor":2,"build_year":2001,"dong_name":"양재동","jibun":"8-24"},{"lawd_cd":"11650","deal_ym":"202005","apt_name":"양재테크노빌","deal_date":"2020-05-21","price_man":79000,"area_m2":83.34,"floor":4,"build_year":2001,"dong_name":"양재동","jibun":"286-6"},{"lawd_cd":"11650","deal_ym":"202005","apt_name":"에이아이디차관주택","deal_date":"2020-05-21","price_man":215000,"area_m2":72.51,"floor":1,"build_year":1974,"dong_name":"반포동","jibun":"968"},{"lawd_cd":"11650","deal_ym":"202005","apt_name":"현대ESA2","deal_date":"2020-05-21","price_man":148000,"area_m2":136.25,"floor":23,"build_year":2003,"dong_name":"서초동","jibun":"1542-6"},{"lawd_cd":"11650","deal_ym":"202005","apt_name":"롯데캐슬클래식","deal_date":"2020-05-22","price_man":218000,"area_m2":120.18,"floor":15,"build_year":2006,"dong_name":"서초동","jibun":"1312-3"},{"lawd_cd":"11650","deal_ym":"202005","apt_name":"방배롯데캐슬로제","deal_date":"2020-05-22","price_man":255000,"area_m2":172.27,"floor":10,"build_year":2009,"dong_name":"방배동","jibun":"849-30"},{"lawd_cd":"11650","deal_ym":"202005","apt_name":"삼풍아파트","deal_date":"2020-05-22","price_man":240000,"area_m2":130.23,"floor":5,"build_year":1988,"dong_name":"서초동","jibun":"1685"},{"lawd_cd":"11650","deal_ym":"202005","apt_name":"서초롯데캐슬84","deal_date":"2020-05-22","price_man":187500,"area_m2":208.63,"floor":15,"build_year":2001,"dong_name":"서초동","jibun":"1642-14"},{"lawd_cd":"11650","deal_ym":"202005","apt_name":"서초한신리빙타워","deal_date":"2020-05-22","price_man":48000,"area_m2":47.87,"floor":2,"build_year":1999,"dong_name":"서초동","jibun":"1533"},{"lawd_cd":"11650","deal_ym":"202005","apt_name":"신반포12","deal_date":"2020-05-22","price_man":172000,"area_m2":105.36,"floor":5,"build_year":1982,"dong_name":"잠원동","jibun":"50-5"},{"lawd_cd":"11650","deal_ym":"202005","apt_name":"신반포2","deal_date":"2020-05-22","price_man":165000,"area_m2":68.91,"floor":1,"build_year":1978,"dong_name":"잠원동","jibun":"73"},{"lawd_cd":"11650","deal_ym":"202005","apt_name":"신반포2","deal_date":"2020-05-22","price_man":186000,"area_m2":68.91,"floor":7,"build_year":1978,"dong_name":"잠원동","jibun":"73"},{"lawd_cd":"11650","deal_ym":"202005","apt_name":"동고","deal_date":"2020-05-23","price_man":104000,"area_m2":84.96,"floor":6,"build_year":1995,"dong_name":"우면동","jibun":"59"},{"lawd_cd":"11650","deal_ym":"202005","apt_name":"래미안서초스위트","deal_date":"2020-05-23","price_man":180000,"area_m2":84.9571,"floor":2,"build_year":2009,"dong_name":"서초동","jibun":"1301-6"},{"lawd_cd":"11650","deal_ym":"202005","apt_name":"래미안서초유니빌","deal_date":"2020-05-23","price_man":34800,"area_m2":34.052,"floor":17,"build_year":2003,"dong_name":"서초동","jibun":"1445-4"},{"lawd_cd":"11650","deal_ym":"202005","apt_name":"롯데캐슬갤럭시","deal_date":"2020-05-23","price_man":200000,"area_m2":106.15,"floor":9,"build_year":2002,"dong_name":"잠원동","jibun":"50"},{"lawd_cd":"11650","deal_ym":"202005","apt_name":"밀라텔쉐르빌","deal_date":"2020-05-23","price_man":78000,"area_m2":65.32,"floor":16,"build_year":2001,"dong_name":"서초동","jibun":"1316-31"},{"lawd_cd":"11650","deal_ym":"202005","apt_name":"반포미도","deal_date":"2020-05-23","price_man":177000,"area_m2":84.96,"floor":5,"build_year":1987,"dong_name":"반포동","jibun":"60-4"},{"lawd_cd":"11650","deal_ym":"202005","apt_name":"반포자이","deal_date":"2020-05-23","price_man":380000,"area_m2":194.515,"floor":15,"build_year":2009,"dong_name":"반포동","jibun":"20-43"},{"lawd_cd":"11650","deal_ym":"202005","apt_name":"반포주공1단지","deal_date":"2020-05-23","price_man":347000,"area_m2":107.47,"floor":1,"build_year":1973,"dong_name":"반포동","jibun":"757"},{"lawd_cd":"11650","deal_ym":"202005","apt_name":"반포훼미리(102동)","deal_date":"2020-05-23","price_man":114000,"area_m2":84.74,"floor":10,"build_year":2003,"dong_name":"반포동","jibun":"712-19"},{"lawd_cd":"11650","deal_ym":"202005","apt_name":"삼풍아파트","deal_date":"2020-05-23","price_man":181000,"area_m2":79.47,"floor":6,"build_year":1988,"dong_name":"서초동","jibun":"1685"},{"lawd_cd":"11650","deal_ym":"202005","apt_name":"삼호가든맨션(5차)","deal_date":"2020-05-23","price_man":248750,"area_m2":153.54,"floor":7,"build_year":1986,"dong_name":"반포동","jibun":"30-1"},{"lawd_cd":"11650","deal_ym":"202005","apt_name":"서초포레스타6단지","deal_date":"2020-05-23","price_man":115000,"area_m2":59.98,"floor":4,"build_year":2015,"dong_name":"신원동","jibun":"619"},{"lawd_cd":"11650","deal_ym":"202005","apt_name":"서초힐스","deal_date":"2020-05-23","price_man":127000,"area_m2":84.96,"floor":7,"build_year":2012,"dong_name":"우면동","jibun":"773"},{"lawd_cd":"11650","deal_ym":"202005","apt_name":"신동아아파트(1차)","deal_date":"2020-05-23","price_man":171000,"area_m2":88.68,"floor":7,"build_year":1978,"dong_name":"서초동","jibun":"1333"},{"lawd_cd":"11650","deal_ym":"202005","apt_name":"신반포2","deal_date":"2020-05-23","price_man":197500,"area_m2":92.2,"floor":2,"build_year":1978,"dong_name":"잠원동","jibun":"73"},{"lawd_cd":"11650","deal_ym":"202005","apt_name":"신반포청구","deal_date":"2020-05-23","price_man":150000,"area_m2":59.91,"floor":8,"build_year":1998,"dong_name":"잠원동","jibun":"63-2"},{"lawd_cd":"11650","deal_ym":"202005","apt_name":"아크로리버파크","deal_date":"2020-05-23","price_man":308000,"area_m2":84.95,"floor":19,"build_year":2016,"dong_name":"반포동","jibun":"2-12"},{"lawd_cd":"11650","deal_ym":"202005","apt_name":"한신그린","deal_date":"2020-05-23","price_man":165000,"area_m2":84.89,"floor":5,"build_year":1993,"dong_name":"잠원동","jibun":"65-8"},{"lawd_cd":"11650","deal_ym":"202005","apt_name":"현대슈퍼빌","deal_date":"2020-05-23","price_man":200000,"area_m2":205.67,"floor":3,"build_year":2003,"dong_name":"서초동","jibun":"1446-11"},{"lawd_cd":"11650","deal_ym":"202005","apt_name":"호반써밋서초파크뷰(토지임대부아파트)","deal_date":"2020-05-23","price_man":87700,"area_m2":59.93,"floor":13,"build_year":2013,"dong_name":"우면동","jibun":"789"},{"lawd_cd":"11650","deal_ym":"202005","apt_name":"동아","deal_date":"2020-05-25","price_man":152000,"area_m2":59.92,"floor":20,"build_year":2002,"dong_name":"잠원동","jibun":"157"},{"lawd_cd":"11650","deal_ym":"202005","apt_name":"롯데캐슬클래식","deal_date":"2020-05-25","price_man":220000,"area_m2":133.45,"floor":16,"build_year":2006,"dong_name":"서초동","jibun":"1312-3"},{"lawd_cd":"11650","deal_ym":"202005","apt_name":"서초트레져","deal_date":"2020-05-25","price_man":110000,"area_m2":224.22,"floor":1,"build_year":2005,"dong_name":"서초동","jibun":"1492-5"},{"lawd_cd":"11650","deal_ym":"202005","apt_name":"신영체르니","deal_date":"2020-05-25","price_man":42500,"area_m2":32.08,"floor":9,"build_year":2002,"dong_name":"양재동","jibun":"90"},{"lawd_cd":"11650","deal_ym":"202005","apt_name":"한신상가","deal_date":"2020-05-25","price_man":149500,"area_m2":106.58,"floor":5,"build_year":1974,"dong_name":"반포동","jibun":"885"},{"lawd_cd":"11650","deal_ym":"202005","apt_name":"한신타워","deal_date":"2020-05-25","price_man":165000,"area_m2":84.93,"floor":7,"build_year":1996,"dong_name":"잠원동","jibun":"71-11"},{"lawd_cd":"11650","deal_ym":"202005","apt_name":"삼풍아파트","deal_date":"2020-05-26","price_man":180000,"area_m2":79.47,"floor":13,"build_year":1988,"dong_name":"서초동","jibun":"1685"},{"lawd_cd":"11650","deal_ym":"202005","apt_name":"서초힐스","deal_date":"2020-05-26","price_man":106000,"area_m2":59.97,"floor":4,"build_year":2012,"dong_name":"우면동","jibun":"773"},{"lawd_cd":"11650","deal_ym":"202005","apt_name":"신동아아파트(1차)","deal_date":"2020-05-26","price_man":188000,"area_m2":101.6,"floor":9,"build_year":1978,"dong_name":"서초동","jibun":"1333"},{"lawd_cd":"11650","deal_ym":"202005","apt_name":"아크로비스타","deal_date":"2020-05-26","price_man":191000,"area_m2":149.08,"floor":19,"build_year":2004,"dong_name":"서초동","jibun":"1685-3"},{"lawd_cd":"11650","deal_ym":"202005","apt_name":"아크로비스타","deal_date":"2020-05-26","price_man":199000,"area_m2":138.96,"floor":34,"build_year":2004,"dong_name":"서초동","jibun":"1685-3"},{"lawd_cd":"11650","deal_ym":"202005","apt_name":"우솔마을서초리슈빌S아파트","deal_date":"2020-05-26","price_man":33500,"area_m2":30.89,"floor":7,"build_year":2014,"dong_name":"우면동","jibun":"764"},{"lawd_cd":"11650","deal_ym":"202005","apt_name":"한신상가","deal_date":"2020-05-26","price_man":147000,"area_m2":156.33,"floor":4,"build_year":1974,"dong_name":"반포동","jibun":"885"},{"lawd_cd":"11650","deal_ym":"202005","apt_name":"더-클라스","deal_date":"2020-05-27","price_man":70000,"area_m2":84.15,"floor":2,"build_year":2004,"dong_name":"양재동","jibun":"402-6"},{"lawd_cd":"11650","deal_ym":"202005","apt_name":"신반포2","deal_date":"2020-05-27","price_man":203000,"area_m2":79.42,"floor":9,"build_year":1978,"dong_name":"잠원동","jibun":"73"},{"lawd_cd":"11650","deal_ym":"202005","apt_name":"롯데캐슬클래식","deal_date":"2020-05-28","price_man":219250,"area_m2":120.18,"floor":13,"build_year":2006,"dong_name":"서초동","jibun":"1312-3"},{"lawd_cd":"11650","deal_ym":"202005","apt_name":"반포미도","deal_date":"2020-05-28","price_man":185000,"area_m2":84.96,"floor":4,"build_year":1987,"dong_name":"반포동","jibun":"60-4"},{"lawd_cd":"11650","deal_ym":"202005","apt_name":"방배우성","deal_date":"2020-05-28","price_man":158000,"area_m2":117.19,"floor":3,"build_year":1991,"dong_name":"방배동","jibun":"2525"},{"lawd_cd":"11650","deal_ym":"202005","apt_name":"방배우성","deal_date":"2020-05-28","price_man":130000,"area_m2":80.2,"floor":11,"build_year":1991,"dong_name":"방배동","jibun":"2525"},{"lawd_cd":"11650","deal_ym":"202005","apt_name":"신반포2","deal_date":"2020-05-28","price_man":225000,"area_m2":92.2,"floor":11,"build_year":1978,"dong_name":"잠원동","jibun":"73"},{"lawd_cd":"11650","deal_ym":"202005","apt_name":"임광","deal_date":"2020-05-28","price_man":184000,"area_m2":136.38,"floor":3,"build_year":1985,"dong_name":"방배동","jibun":"1015"},{"lawd_cd":"11650","deal_ym":"202005","apt_name":"현대슈퍼빌","deal_date":"2020-05-28","price_man":180000,"area_m2":147.86,"floor":20,"build_year":2003,"dong_name":"서초동","jibun":"1446-11"},{"lawd_cd":"11650","deal_ym":"202005","apt_name":"래미안서초유니빌","deal_date":"2020-05-29","price_man":34000,"area_m2":45.255,"floor":3,"build_year":2003,"dong_name":"서초동","jibun":"1445-4"},{"lawd_cd":"11650","deal_ym":"202005","apt_name":"롯데캐슬갤럭시(50-1)","deal_date":"2020-05-29","price_man":226000,"area_m2":132.16,"floor":12,"build_year":2004,"dong_name":"잠원동","jibun":"50-1"},{"lawd_cd":"11650","deal_ym":"202005","apt_name":"롯데캐슬클래식","deal_date":"2020-05-29","price_man":212000,"area_m2":120.18,"floor":14,"build_year":2006,"dong_name":"서초동","jibun":"1312-3"},{"lawd_cd":"11650","deal_ym":"202005","apt_name":"반포자이","deal_date":"2020-05-29","price_man":345000,"area_m2":165.446,"floor":2,"build_year":2009,"dong_name":"반포동","jibun":"20-43"},{"lawd_cd":"11650","deal_ym":"202005","apt_name":"방배현대멤피스2","deal_date":"2020-05-29","price_man":180000,"area_m2":162.8,"floor":14,"build_year":2002,"dong_name":"방배동","jibun":"982-1"},{"lawd_cd":"11650","deal_ym":"202005","apt_name":"브라운스톤로얄스위트서초","deal_date":"2020-05-29","price_man":145000,"area_m2":139.54,"floor":3,"build_year":2005,"dong_name":"서초동","jibun":"1492-4"},{"lawd_cd":"11650","deal_ym":"202005","apt_name":"서초힐스","deal_date":"2020-05-29","price_man":135000,"area_m2":84.97,"floor":21,"build_year":2012,"dong_name":"우면동","jibun":"773"},{"lawd_cd":"11650","deal_ym":"202005","apt_name":"신동아","deal_date":"2020-05-29","price_man":178000,"area_m2":139.74,"floor":2,"build_year":1981,"dong_name":"방배동","jibun":"988-1"},{"lawd_cd":"11650","deal_ym":"202005","apt_name":"신반포12","deal_date":"2020-05-29","price_man":180000,"area_m2":105.36,"floor":9,"build_year":1982,"dong_name":"잠원동","jibun":"50-5"},{"lawd_cd":"11650","deal_ym":"202005","apt_name":"신반포12","deal_date":"2020-05-29","price_man":129000,"area_m2":55.45,"floor":12,"build_year":1982,"dong_name":"잠원동","jibun":"50-5"},{"lawd_cd":"11650","deal_ym":"202005","apt_name":"신영체르니","deal_date":"2020-05-29","price_man":47000,"area_m2":35.91,"floor":3,"build_year":2002,"dong_name":"양재동","jibun":"90"},{"lawd_cd":"11650","deal_ym":"202005","apt_name":"아크로비스타","deal_date":"2020-05-29","price_man":183000,"area_m2":138.96,"floor":17,"build_year":2004,"dong_name":"서초동","jibun":"1685-3"},{"lawd_cd":"11650","deal_ym":"202005","apt_name":"에이아이디차관주택","deal_date":"2020-05-29","price_man":220000,"area_m2":72.51,"floor":2,"build_year":1974,"dong_name":"반포동","jibun":"968"},{"lawd_cd":"11650","deal_ym":"202005","apt_name":"팔라티노","deal_date":"2020-05-29","price_man":149000,"area_m2":139.045,"floor":4,"build_year":2012,"dong_name":"방배동","jibun":"810-14"},{"lawd_cd":"11650","deal_ym":"202005","apt_name":"대림서초리시온","deal_date":"2020-05-30","price_man":46700,"area_m2":45.72,"floor":9,"build_year":2003,"dong_name":"서초동","jibun":"1671-5"},{"lawd_cd":"11650","deal_ym":"202005","apt_name":"래미안서초유니빌","deal_date":"2020-05-30","price_man":51500,"area_m2":50.19,"floor":5,"build_year":2003,"dong_name":"서초동","jibun":"1445-4"},{"lawd_cd":"11650","deal_ym":"202005","apt_name":"래미안신반포팰리스","deal_date":"2020-05-30","price_man":265000,"area_m2":104.04,"floor":7,"build_year":2016,"dong_name":"잠원동","jibun":"158"},{"lawd_cd":"11650","deal_ym":"202005","apt_name":"롯데캐슬쥬피터","deal_date":"2020-05-30","price_man":134000,"area_m2":95.33,"floor":9,"build_year":2003,"dong_name":"서초동","jibun":"1359-50"},{"lawd_cd":"11650","deal_ym":"202005","apt_name":"방배우성","deal_date":"2020-05-30","price_man":121500,"area_m2":80.2,"floor":1,"build_year":1991,"dong_name":"방배동","jibun":"2525"},{"lawd_cd":"11650","deal_ym":"202005","apt_name":"방배임광3차","deal_date":"2020-05-30","price_man":144000,"area_m2":100.82,"floor":10,"build_year":1988,"dong_name":"방배동","jibun":"1010-1"},{"lawd_cd":"11650","deal_ym":"202005","apt_name":"서초동대우디오빌프라임","deal_date":"2020-05-30","price_man":99000,"area_m2":81.97,"floor":12,"build_year":2005,"dong_name":"서초동","jibun":"1337-22"},{"lawd_cd":"11650","deal_ym":"202005","apt_name":"서초이오빌","deal_date":"2020-05-30","price_man":33900,"area_m2":45.96,"floor":7,"build_year":2003,"dong_name":"서초동","jibun":"1593-7"},{"lawd_cd":"11650","deal_ym":"202005","apt_name":"서초포레스타3단지","deal_date":"2020-05-30","price_man":98500,"area_m2":59.96,"floor":1,"build_year":2014,"dong_name":"신원동","jibun":"568"},{"lawd_cd":"11650","deal_ym":"202005","apt_name":"서초포레스타5단지","deal_date":"2020-05-30","price_man":140500,"area_m2":84.81,"floor":6,"build_year":2014,"dong_name":"신원동","jibun":"579"},{"lawd_cd":"11650","deal_ym":"202005","apt_name":"서초래미안","deal_date":"2020-05-31","price_man":192000,"area_m2":126.31,"floor":1,"build_year":2003,"dong_name":"서초동","jibun":"1682"},{"lawd_cd":"11650","deal_ym":"202005","apt_name":"서초훼미리하우스","deal_date":"2020-05-31","price_man":87000,"area_m2":59.57,"floor":3,"build_year":2017,"dong_name":"방배동","jibun":"917-4"},{"lawd_cd":"11650","deal_ym":"202005","apt_name":"아크로리버파크","deal_date":"2020-05-31","price_man":330000,"area_m2":84.95,"floor":20,"build_year":2016,"dong_name":"반포동","jibun":"2-12"},{"lawd_cd":"11650","deal_ym":"202005","apt_name":"킴스빌리지","deal_date":"2020-05-31","price_man":81800,"area_m2":37.38,"floor":9,"build_year":1996,"dong_name":"잠원동","jibun":"71-12"}]